LICENSE
README.md
setup.cfg
setup.py
bnn/__init__.py
bnn/bconfig.py
bnn/binarize.py
bnn/engine.py
bnn/ops.py
bnn/version.py
bnn.egg-info/PKG-INFO
bnn.egg-info/SOURCES.txt
bnn.egg-info/dependency_links.txt
bnn.egg-info/requires.txt
bnn.egg-info/top_level.txt
bnn.egg-info/zip-safe
bnn/layers/__init__.py
bnn/layers/conv.py
bnn/layers/helpers.py
bnn/layers/linear.py
bnn/models/__init__.py
bnn/models/bats.py
bnn/models/resnet.py
bnn/models/layers/__init__.py
bnn/models/layers/bats_ops.py
bnn/models/layers/common.py
bnn/models/layers/hierarchical_block.py
bnn/models/layers/res_block.py
test/test_binarize.py
test/test_engine.py
test/test_layers.py