Metadata-Version: 2.1
Name: bnn
Version: 0.1.2
Summary: Binarize deep convolutional neural networks using python and pytorch
Home-page: https://github.com/1adrianb/binary-networks-pytorch
Author: Adrian Bulat
Author-email: adrian@adrianbulat.com
License: BSD
Keywords: artificial intelligence,convolutional neural network,binary networks,quantization,pytorch
Platform: UNKNOWN
Classifier: Development Status :: 4 - Beta
Classifier: Operating System :: OS Independent
Classifier: Intended Audience :: Developers
Classifier: Intended Audience :: Education
Classifier: Intended Audience :: Science/Research
Classifier: Topic :: Scientific/Engineering
Classifier: Topic :: Scientific/Engineering :: Artificial Intelligence
Classifier: Topic :: Software Development :: Libraries
Classifier: Topic :: Software Development :: Libraries :: Python Modules
Classifier: License :: OSI Approved :: BSD License
Classifier: Natural Language :: English
Classifier: Programming Language :: Python :: 3.7
Classifier: Programming Language :: Python :: 3.8
Classifier: Programming Language :: Python :: 3.9
